README.md
setup.py
eeg_framework/__init__.py
eeg_framework.egg-info/PKG-INFO
eeg_framework.egg-info/SOURCES.txt
eeg_framework.egg-info/dependency_links.txt
eeg_framework.egg-info/top_level.txt