Metadata-Version: 1.2
Name: eeg-framework
Version: 0.1
Summary: GCPDS: eeg_framework
Home-page: UNKNOWN
Author: Yeison Cardona
Author-email: yeisoneng@gmail.com
Maintainer: Yeison Cardona
Maintainer-email: yeisoneng@gmail.com
License: BSD License
Download-URL: https://bitbucket.org/gcpds/eeg_framework/downloads/
Platform: UNKNOWN
